{
    "Module": [
        {
            "name": "Module",
            "leader": "",
            "children": [
                {
                    "kind": "grammar",
                    "relation": "body",
                    "nonterminal": "statements",
                    "format": "InLine",
                    "follower": ""
                }
            ]
        }
    ],
    "CompareRight": [
        {
            "name": "CompareRight",
            "leader": "",
            "children": [
                {
                    "kind": "grammar",
                    "relation": "op",
                    "nonterminal": "cmpop",
                    "format": "InLine",
                    "follower": " "
                },
                {
                    "kind": "grammar",
                    "relation": "rand",
                    "nonterminal": "expr",
                    "format": "InLine",
                    "follower": ""
                }
            ]
        }
    ],
    "ExceptHandler": [
        {
            "name": "ExceptHandler",
            "leader": "except ",
            "children": [
                {
                    "kind": "grammar",
                    "relation": "arg",
                    "nonterminal": "except_arg",
                    "format": "InLine",
                    "follower": ":"
                },
                {
                    "kind": "grammar",
                    "relation": "body",
                    "nonterminal": "statements",
                    "format": "IndentLine",
                    "follower": ""
                }
            ]
        }
    ],
    "Param": [
        {
            "name": "Param",
            "leader": "",
            "children": [
                {
                    "kind": "vocab",
                    "relation": "name",
                    "choices_id": "identifier"
                },
                {
                    "kind": "grammar",
                    "relation": "type",
                    "nonterminal": "param_type",
                    "format": "InLine",
                    "follower": ""
                },
                {
                    "kind": "grammar",
                    "relation": "default",
                    "nonterminal": "param_default",
                    "format": "InLine",
                    "follower": ""
                }
            ]
        }
    ],
    "Field": [
        {
            "name": "Field",
            "leader": "",
            "children": [
                {
                    "kind": "grammar",
                    "relation": "key",
                    "nonterminal": "expr",
                    "format": "InLine",
                    "follower": " : "
                },
                {
                    "kind": "grammar",
                    "relation": "contents",
                    "nonterminal": "expr",
                    "format": "InLine",
                    "follower": ""
                }
            ]
        }
    ],
    "ImportName": [
        {
            "name": "ImportName",
            "leader": "",
            "children": [
                {
                    "kind": "vocab",
                    "relation": "name",
                    "choices_id": "module_identifier"
                },
                {
                    "kind": "grammar",
                    "relation": "as_name",
                    "nonterminal": "alias",
                    "format": "InLine",
                    "follower": ""
                }
            ]
        }
    ],
    "Withitem": [
        {
            "name": "Withitem",
            "leader": "",
            "children": [
                {
                    "kind": "grammar",
                    "relation": "contet",
                    "nonterminal": "expr",
                    "format": "InLine",
                    "follower": ""
                },
                {
                    "kind": "grammar",
                    "relation": "target",
                    "nonterminal": "alias_expr",
                    "format": "InLine",
                    "follower": ""
                }
            ]
        }
    ],
    "ClassDef": [
        {
            "name": "ClassDef",
            "leader": "class ",
            "children": [
                {
                    "kind": "vocab",
                    "relation": "name",
                    "choices_id": "identifier"
                },
                {
                    "kind": "grammar",
                    "relation": "bs",
                    "nonterminal": "bases",
                    "format": "InLine",
                    "follower": ":"
                },
                {
                    "kind": "grammar",
                    "relation": "body",
                    "nonterminal": "statements",
                    "format": "IndentLine",
                    "follower": ""
                }
            ]
        }
    ],
    "ElifBlock": [
        {
            "name": "ElifBlock",
            "leader": "elif ",
            "children": [
                {
                    "kind": "grammar",
                    "relation": "test",
                    "nonterminal": "expr",
                    "format": "InLine",
                    "follower": ":"
                },
                {
                    "kind": "grammar",
                    "relation": "body",
                    "nonterminal": "statements",
                    "format": "IndentLine",
                    "follower": ""
                }
            ]
        }
    ],
    "ElseBlock": [
        {
            "name": "ElseBlock",
            "leader": "else:",
            "children": [
                {
                    "kind": "grammar",
                    "relation": "body",
                    "nonterminal": "statements",
                    "format": "IndentLine",
                    "follower": ""
                }
            ]
        }
    ],
    "FinallyBlock": [
        {
            "name": "FinallyBlock",
            "leader": "finally:",
            "children": [
                {
                    "kind": "grammar",
                    "relation": "body",
                    "nonterminal": "statements",
                    "format": "IndentLine",
                    "follower": ""
                }
            ]
        }
    ],
    "return_type": [
        {
            "name": "SomeReturnType",
            "leader": " -> ",
            "children": [
                {
                    "kind": "grammar",
                    "relation": "contents",
                    "nonterminal": "expr",
                    "format": "InLine",
                    "follower": ""
                }
            ]
        },
        {
            "name": "NoReturnType",
            "leader": "",
            "children": []
        }
    ],
    "module_id": [
        {
            "name": "SomeModuleId",
            "leader": "",
            "children": [
                {
                    "kind": "vocab",
                    "relation": "contents",
                    "choices_id": "module_identifier"
                }
            ]
        },
        {
            "name": "NoModuleId",
            "leader": ".",
            "children": []
        }
    ],
    "except_arg": [
        {
            "name": "SomeExceptArg",
            "leader": " ",
            "children": [
                {
                    "kind": "grammar",
                    "relation": "contents",
                    "nonterminal": "expr",
                    "format": "InLine",
                    "follower": ""
                }
            ]
        },
        {
            "name": "SomeExceptArgName",
            "leader": " ",
            "children": [
                {
                    "kind": "grammar",
                    "relation": "contents",
                    "nonterminal": "expr",
                    "format": "InLine",
                    "follower": " as "
                },
                {
                    "kind": "vocab",
                    "relation": "name",
                    "choices_id": "identifier"
                }
            ]
        },
        {
            "name": "NoExceptArg",
            "leader": "",
            "children": []
        }
    ],
    "param_type": [
        {
            "name": "SomeParamType",
            "leader": " : ",
            "children": [
                {
                    "kind": "grammar",
                    "relation": "contents",
                    "nonterminal": "expr",
                    "format": "InLine",
                    "follower": ""
                }
            ]
        },
        {
            "name": "NoParamType",
            "leader": "",
            "children": []
        }
    ],
    "param_default": [
        {
            "name": "SomeParamDefault",
            "leader": " = ",
            "children": [
                {
                    "kind": "grammar",
                    "relation": "contents",
                    "nonterminal": "expr",
                    "format": "InLine",
                    "follower": ""
                }
            ]
        },
        {
            "name": "NoParamDefault",
            "leader": "",
            "children": []
        }
    ],
    "parameters_d": [
        {
            "name": "ConsKwParam",
            "leader": "",
            "children": [
                {
                    "kind": "grammar",
                    "relation": "head",
                    "nonterminal": "Param",
                    "format": "InLine",
                    "follower": ", "
                },
                {
                    "kind": "grammar",
                    "relation": "tail",
                    "nonterminal": "parameters_d",
                    "format": "InLine",
                    "follower": ""
                }
            ]
        },
        {
            "name": "SingleKwParam",
            "leader": "",
            "children": [
                {
                    "kind": "grammar",
                    "relation": "contents",
                    "nonterminal": "Param",
                    "format": "InLine",
                    "follower": ""
                }
            ]
        },
        {
            "name": "DictionarySplatParam",
            "leader": "**",
            "children": [
                {
                    "kind": "grammar",
                    "relation": "contents",
                    "nonterminal": "Param",
                    "format": "InLine",
                    "follower": ""
                }
            ]
        }
    ],
    "parameters_c": [
        {
            "name": "SingleListSplatParam",
            "leader": "*",
            "children": [
                {
                    "kind": "grammar",
                    "relation": "contents",
                    "nonterminal": "Param",
                    "format": "InLine",
                    "follower": ""
                }
            ]
        },
        {
            "name": "TransListSplatParam",
            "leader": "*",
            "children": [
                {
                    "kind": "grammar",
                    "relation": "head",
                    "nonterminal": "Param",
                    "format": "InLine",
                    "follower": ", "
                },
                {
                    "kind": "grammar",
                    "relation": "tail",
                    "nonterminal": "parameters_d",
                    "format": "InLine",
                    "follower": ""
                }
            ]
        },
        {
            "name": "ParamsD",
            "leader": "*, ",
            "children": [
                {
                    "kind": "grammar",
                    "relation": "contents",
                    "nonterminal": "parameters_d",
                    "format": "InLine",
                    "follower": ""
                }
            ]
        }
    ],
    "parameters_b": [
        {
            "name": "ConsParam",
            "leader": "",
            "children": [
                {
                    "kind": "grammar",
                    "relation": "head",
                    "nonterminal": "Param",
                    "format": "InLine",
                    "follower": ", "
                },
                {
                    "kind": "grammar",
                    "relation": "tail",
                    "nonterminal": "parameters_b",
                    "format": "InLine",
                    "follower": ""
                }
            ]
        },
        {
            "name": "SingleParam",
            "leader": "",
            "children": [
                {
                    "kind": "grammar",
                    "relation": "contents",
                    "nonterminal": "Param",
                    "format": "InLine",
                    "follower": ""
                }
            ]
        },
        {
            "name": "ParamsC",
            "leader": "",
            "children": [
                {
                    "kind": "grammar",
                    "relation": "contents",
                    "nonterminal": "parameters_c",
                    "format": "InLine",
                    "follower": ""
                }
            ]
        }
    ],
    "parameters": [
        {
            "name": "ParamsA",
            "leader": "",
            "children": [
                {
                    "kind": "grammar",
                    "relation": "contents",
                    "nonterminal": "parameters_a",
                    "format": "InLine",
                    "follower": ""
                }
            ]
        },
        {
            "name": "ParamsB",
            "leader": "",
            "children": [
                {
                    "kind": "grammar",
                    "relation": "contents",
                    "nonterminal": "parameters_b",
                    "format": "InLine",
                    "follower": ""
                }
            ]
        },
        {
            "name": "NoParam",
            "leader": "",
            "children": []
        }
    ],
    "parameters_a": [
        {
            "name": "ConsPosParam",
            "leader": "",
            "children": [
                {
                    "kind": "grammar",
                    "relation": "head",
                    "nonterminal": "Param",
                    "format": "InLine",
                    "follower": ", "
                },
                {
                    "kind": "grammar",
                    "relation": "tail",
                    "nonterminal": "parameters_a",
                    "format": "InLine",
                    "follower": ""
                }
            ]
        },
        {
            "name": "SinglePosParam",
            "leader": "",
            "children": [
                {
                    "kind": "grammar",
                    "relation": "contents",
                    "nonterminal": "Param",
                    "format": "InLine",
                    "follower": ", /"
                }
            ]
        },
        {
            "name": "TransPosParam",
            "leader": "",
            "children": [
                {
                    "kind": "grammar",
                    "relation": "head",
                    "nonterminal": "Param",
                    "format": "InLine",
                    "follower": ", /, "
                },
                {
                    "kind": "grammar",
                    "relation": "tail",
                    "nonterminal": "parameters_b",
                    "format": "InLine",
                    "follower": ""
                }
            ]
        }
    ],
    "keyword": [
        {
            "name": "NamedKeyword",
            "leader": "",
            "children": [
                {
                    "kind": "vocab",
                    "relation": "name",
                    "choices_id": "identifier"
                },
                {
                    "kind": "grammar",
                    "relation": "contents",
                    "nonterminal": "expr",
                    "format": "InLine",
                    "follower": ""
                }
            ]
        },
        {
            "name": "SplatKeyword",
            "leader": "**",
            "children": [
                {
                    "kind": "grammar",
                    "relation": "contents",
                    "nonterminal": "expr",
                    "format": "InLine",
                    "follower": ""
                }
            ]
        }
    ],
    "alias": [
        {
            "name": "SomeAlias",
            "leader": " as ",
            "children": [
                {
                    "kind": "vocab",
                    "relation": "contents",
                    "choices_id": "identifier"
                }
            ]
        },
        {
            "name": "NoAlias",
            "leader": "",
            "children": []
        }
    ],
    "alias_expr": [
        {
            "name": "SomeAliasExpr",
            "leader": " as ",
            "children": [
                {
                    "kind": "grammar",
                    "relation": "contents",
                    "nonterminal": "expr",
                    "format": "InLine",
                    "follower": ""
                }
            ]
        },
        {
            "name": "NoAliasExpr",
            "leader": "",
            "children": []
        }
    ],
    "bases": [
        {
            "name": "SomeBases",
            "leader": "(",
            "children": [
                {
                    "kind": "grammar",
                    "relation": "bases",
                    "nonterminal": "bases_a",
                    "format": "InLine",
                    "follower": ")"
                }
            ]
        },
        {
            "name": "NoBases",
            "leader": "",
            "children": []
        }
    ],
    "bases_a": [
        {
            "name": "ConsBase",
            "leader": "",
            "children": [
                {
                    "kind": "grammar",
                    "relation": "head",
                    "nonterminal": "expr",
                    "format": "InLine",
                    "follower": ", "
                },
                {
                    "kind": "grammar",
                    "relation": "tail",
                    "nonterminal": "bases_a",
                    "format": "InLine",
                    "follower": ""
                }
            ]
        },
        {
            "name": "SingleBase",
            "leader": "",
            "children": [
                {
                    "kind": "grammar",
                    "relation": "contents",
                    "nonterminal": "expr",
                    "format": "InLine",
                    "follower": ""
                }
            ]
        },
        {
            "name": "KeywordsBase",
            "leader": "",
            "children": [
                {
                    "kind": "grammar",
                    "relation": "kws",
                    "nonterminal": "keywords",
                    "format": "InLine",
                    "follower": ""
                }
            ]
        }
    ],
    "keywords": [
        {
            "name": "ConsKeyword",
            "leader": "",
            "children": [
                {
                    "kind": "grammar",
                    "relation": "head",
                    "nonterminal": "keyword",
                    "format": "InLine",
                    "follower": ", "
                },
                {
                    "kind": "grammar",
                    "relation": "tail",
                    "nonterminal": "keywords",
                    "format": "InLine",
                    "follower": ""
                }
            ]
        },
        {
            "name": "SingleKeyword",
            "leader": "",
            "children": [
                {
                    "kind": "grammar",
                    "relation": "contents",
                    "nonterminal": "keyword",
                    "format": "InLine",
                    "follower": ""
                }
            ]
        }
    ],
    "comparisons": [
        {
            "name": "ConsCompareRight",
            "leader": "",
            "children": [
                {
                    "kind": "grammar",
                    "relation": "head",
                    "nonterminal": "CompareRight",
                    "format": "InLine",
                    "follower": " "
                },
                {
                    "kind": "grammar",
                    "relation": "tail",
                    "nonterminal": "comparisons",
                    "format": "InLine",
                    "follower": ""
                }
            ]
        },
        {
            "name": "SingleCompareRight",
            "leader": "",
            "children": [
                {
                    "kind": "grammar",
                    "relation": "contents",
                    "nonterminal": "CompareRight",
                    "format": "InLine",
                    "follower": ""
                }
            ]
        }
    ],
    "option_expr": [
        {
            "name": "SomeExpr",
            "leader": "",
            "children": [
                {
                    "kind": "grammar",
                    "relation": "contents",
                    "nonterminal": "expr",
                    "format": "InLine",
                    "follower": ""
                }
            ]
        },
        {
            "name": "NoExpr",
            "leader": "",
            "children": []
        }
    ],
    "comma_exprs": [
        {
            "name": "ConsExpr",
            "leader": "",
            "children": [
                {
                    "kind": "grammar",
                    "relation": "head",
                    "nonterminal": "expr",
                    "format": "InLine",
                    "follower": ", "
                },
                {
                    "kind": "grammar",
                    "relation": "tail",
                    "nonterminal": "comma_exprs",
                    "format": "InLine",
                    "follower": ""
                }
            ]
        },
        {
            "name": "SingleExpr",
            "leader": "",
            "children": [
                {
                    "kind": "grammar",
                    "relation": "contents",
                    "nonterminal": "expr",
                    "format": "InLine",
                    "follower": ""
                }
            ]
        }
    ],
    "target_exprs": [
        {
            "name": "ConsTargetExpr",
            "leader": "",
            "children": [
                {
                    "kind": "grammar",
                    "relation": "head",
                    "nonterminal": "expr",
                    "format": "InLine",
                    "follower": " = "
                },
                {
                    "kind": "grammar",
                    "relation": "tail",
                    "nonterminal": "target_exprs",
                    "format": "InLine",
                    "follower": ""
                }
            ]
        },
        {
            "name": "SingleTargetExpr",
            "leader": "",
            "children": [
                {
                    "kind": "grammar",
                    "relation": "contents",
                    "nonterminal": "expr",
                    "format": "InLine",
                    "follower": ""
                }
            ]
        }
    ],
    "decorators": [
        {
            "name": "ConsDec",
            "leader": "@",
            "children": [
                {
                    "kind": "grammar",
                    "relation": "head",
                    "nonterminal": "expr",
                    "format": "InLine",
                    "follower": ""
                },
                {
                    "kind": "grammar",
                    "relation": "tail",
                    "nonterminal": "decorators",
                    "format": "InLine",
                    "follower": ""
                }
            ]
        },
        {
            "name": "NoDec",
            "leader": "",
            "children": []
        }
    ],
    "constraint_filters": [
        {
            "name": "ConsFilter",
            "leader": "if ",
            "children": [
                {
                    "kind": "grammar",
                    "relation": "head",
                    "nonterminal": "expr",
                    "format": "NewLine",
                    "follower": ""
                },
                {
                    "kind": "grammar",
                    "relation": "tail",
                    "nonterminal": "constraint_filters",
                    "format": "InLine",
                    "follower": ""
                }
            ]
        },
        {
            "name": "SingleFilter",
            "leader": "if ",
            "children": [
                {
                    "kind": "grammar",
                    "relation": "contents",
                    "nonterminal": "expr",
                    "format": "NewLine",
                    "follower": ""
                }
            ]
        },
        {
            "name": "NoFilter",
            "leader": "",
            "children": []
        }
    ],
    "sequence_string": [
        {
            "name": "ConsStr",
            "leader": "",
            "children": [
                {
                    "kind": "vocab",
                    "relation": "head",
                    "choices_id": "string"
                },
                {
                    "kind": "grammar",
                    "relation": "tail",
                    "nonterminal": "sequence_string",
                    "format": "InLine",
                    "follower": ""
                }
            ]
        },
        {
            "name": "SingleStr",
            "leader": "",
            "children": [
                {
                    "kind": "vocab",
                    "relation": "contents",
                    "choices_id": "string"
                }
            ]
        }
    ],
    "arguments": [
        {
            "name": "ConsArg",
            "leader": "",
            "children": [
                {
                    "kind": "grammar",
                    "relation": "head",
                    "nonterminal": "expr",
                    "format": "InLine",
                    "follower": ", "
                },
                {
                    "kind": "grammar",
                    "relation": "tail",
                    "nonterminal": "arguments",
                    "format": "InLine",
                    "follower": ""
                }
            ]
        },
        {
            "name": "SingleArg",
            "leader": "",
            "children": [
                {
                    "kind": "grammar",
                    "relation": "contents",
                    "nonterminal": "expr",
                    "format": "InLine",
                    "follower": ""
                }
            ]
        },
        {
            "name": "KeywordsArg",
            "leader": "",
            "children": [
                {
                    "kind": "grammar",
                    "relation": "kws",
                    "nonterminal": "keywords",
                    "format": "InLine",
                    "follower": ""
                }
            ]
        }
    ],
    "dictionary_contents": [
        {
            "name": "ConsField",
            "leader": "",
            "children": [
                {
                    "kind": "grammar",
                    "relation": "head",
                    "nonterminal": "Field",
                    "format": "InLine",
                    "follower": ", "
                },
                {
                    "kind": "grammar",
                    "relation": "tail",
                    "nonterminal": "dictionary_contents",
                    "format": "NewLine",
                    "follower": ""
                }
            ]
        },
        {
            "name": "SingleField",
            "leader": "",
            "children": [
                {
                    "kind": "grammar",
                    "relation": "contents",
                    "nonterminal": "Field",
                    "format": "InLine",
                    "follower": ""
                }
            ]
        }
    ],
    "sequence_var": [
        {
            "name": "ConsId",
            "leader": "",
            "children": [
                {
                    "kind": "vocab",
                    "relation": "head",
                    "choices_id": "identifier"
                },
                {
                    "kind": "grammar",
                    "relation": "tail",
                    "nonterminal": "sequence_var",
                    "format": "InLine",
                    "follower": ""
                }
            ]
        },
        {
            "name": "SingleId",
            "leader": "",
            "children": [
                {
                    "kind": "vocab",
                    "relation": "contents",
                    "choices_id": "identifier"
                }
            ]
        }
    ],
    "sequence_ImportName": [
        {
            "name": "ConsImportName",
            "leader": "",
            "children": [
                {
                    "kind": "grammar",
                    "relation": "head",
                    "nonterminal": "ImportName",
                    "format": "InLine",
                    "follower": ", "
                },
                {
                    "kind": "grammar",
                    "relation": "tail",
                    "nonterminal": "sequence_ImportName",
                    "format": "InLine",
                    "follower": ""
                }
            ]
        },
        {
            "name": "SingleImportName",
            "leader": "",
            "children": [
                {
                    "kind": "grammar",
                    "relation": "contents",
                    "nonterminal": "ImportName",
                    "format": "InLine",
                    "follower": ""
                }
            ]
        }
    ],
    "sequence_Withitem": [
        {
            "name": "ConsWithitem",
            "leader": "",
            "children": [
                {
                    "kind": "grammar",
                    "relation": "head",
                    "nonterminal": "Withitem",
                    "format": "InLine",
                    "follower": ", "
                },
                {
                    "kind": "grammar",
                    "relation": "tail",
                    "nonterminal": "sequence_Withitem",
                    "format": "InLine",
                    "follower": ""
                }
            ]
        },
        {
            "name": "SingleWithitem",
            "leader": "",
            "children": [
                {
                    "kind": "grammar",
                    "relation": "contents",
                    "nonterminal": "Withitem",
                    "format": "InLine",
                    "follower": ""
                }
            ]
        }
    ],
    "statements": [
        {
            "name": "ConsStmt",
            "leader": "",
            "children": [
                {
                    "kind": "grammar",
                    "relation": "head",
                    "nonterminal": "stmt",
                    "format": "InLine",
                    "follower": ""
                },
                {
                    "kind": "grammar",
                    "relation": "tail",
                    "nonterminal": "statements",
                    "format": "NewLine",
                    "follower": ""
                }
            ]
        },
        {
            "name": "SingleStmt",
            "leader": "",
            "children": [
                {
                    "kind": "grammar",
                    "relation": "contents",
                    "nonterminal": "stmt",
                    "format": "InLine",
                    "follower": ""
                }
            ]
        }
    ],
    "comprehension_constraints": [
        {
            "name": "ConsConstraint",
            "leader": "",
            "children": [
                {
                    "kind": "grammar",
                    "relation": "head",
                    "nonterminal": "constraint",
                    "format": "InLine",
                    "follower": ""
                },
                {
                    "kind": "grammar",
                    "relation": "tail",
                    "nonterminal": "comprehension_constraints",
                    "format": "NewLine",
                    "follower": ""
                }
            ]
        },
        {
            "name": "SingleConstraint",
            "leader": "",
            "children": [
                {
                    "kind": "grammar",
                    "relation": "contents",
                    "nonterminal": "constraint",
                    "format": "InLine",
                    "follower": ""
                }
            ]
        }
    ],
    "sequence_ExceptHandler": [
        {
            "name": "ConsExceptHandler",
            "leader": "",
            "children": [
                {
                    "kind": "grammar",
                    "relation": "head",
                    "nonterminal": "ExceptHandler",
                    "format": "InLine",
                    "follower": ""
                },
                {
                    "kind": "grammar",
                    "relation": "tail",
                    "nonterminal": "sequence_ExceptHandler",
                    "format": "NewLine",
                    "follower": ""
                }
            ]
        },
        {
            "name": "SingleExceptHandler",
            "leader": "",
            "children": [
                {
                    "kind": "grammar",
                    "relation": "contents",
                    "nonterminal": "ExceptHandler",
                    "format": "InLine",
                    "follower": ""
                }
            ]
        }
    ],
    "conditions": [
        {
            "name": "ElifCond",
            "leader": "",
            "children": [
                {
                    "kind": "grammar",
                    "relation": "contents",
                    "nonterminal": "ElifBlock",
                    "format": "NewLine",
                    "follower": ""
                },
                {
                    "kind": "grammar",
                    "relation": "tail",
                    "nonterminal": "conditions",
                    "format": "InLine",
                    "follower": ""
                }
            ]
        },
        {
            "name": "ElseCond",
            "leader": "",
            "children": [
                {
                    "kind": "grammar",
                    "relation": "contents",
                    "nonterminal": "ElseBlock",
                    "format": "NewLine",
                    "follower": ""
                }
            ]
        },
        {
            "name": "NoCond",
            "leader": "",
            "children": []
        }
    ],
    "function_def": [
        {
            "name": "FunctionDef",
            "leader": "def ",
            "children": [
                {
                    "kind": "vocab",
                    "relation": "name",
                    "choices_id": "identifier"
                },
                {
                    "kind": "grammar",
                    "relation": "params",
                    "nonterminal": "parameters",
                    "format": "InLine",
                    "follower": ")"
                },
                {
                    "kind": "grammar",
                    "relation": "ret_typ",
                    "nonterminal": "return_type",
                    "format": "InLine",
                    "follower": ":"
                },
                {
                    "kind": "grammar",
                    "relation": "body",
                    "nonterminal": "statements",
                    "format": "IndentLine",
                    "follower": ""
                }
            ]
        },
        {
            "name": "AsyncFunctionDef",
            "leader": "def ",
            "children": [
                {
                    "kind": "vocab",
                    "relation": "name",
                    "choices_id": "identifier"
                },
                {
                    "kind": "grammar",
                    "relation": "params",
                    "nonterminal": "parameters",
                    "format": "InLine",
                    "follower": ")"
                },
                {
                    "kind": "grammar",
                    "relation": "ret_typ",
                    "nonterminal": "return_type",
                    "format": "InLine",
                    "follower": ":"
                },
                {
                    "kind": "grammar",
                    "relation": "body",
                    "nonterminal": "statements",
                    "format": "IndentLine",
                    "follower": ""
                }
            ]
        }
    ],
    "stmt": [
        {
            "name": "DecFunctionDef",
            "leader": "",
            "children": [
                {
                    "kind": "grammar",
                    "relation": "decs",
                    "nonterminal": "decorators",
                    "format": "InLine",
                    "follower": ""
                },
                {
                    "kind": "grammar",
                    "relation": "fun_def",
                    "nonterminal": "function_def",
                    "format": "NewLine",
                    "follower": ""
                }
            ]
        },
        {
            "name": "DecAsyncFunctionDef",
            "leader": "",
            "children": [
                {
                    "kind": "grammar",
                    "relation": "decs",
                    "nonterminal": "decorators",
                    "format": "InLine",
                    "follower": ""
                },
                {
                    "kind": "grammar",
                    "relation": "fun_def",
                    "nonterminal": "function_def",
                    "format": "NewLine",
                    "follower": ""
                }
            ]
        },
        {
            "name": "DecClassDef",
            "leader": "",
            "children": [
                {
                    "kind": "grammar",
                    "relation": "decs",
                    "nonterminal": "decorators",
                    "format": "InLine",
                    "follower": ""
                },
                {
                    "kind": "grammar",
                    "relation": "class_def",
                    "nonterminal": "ClassDef",
                    "format": "NewLine",
                    "follower": ""
                }
            ]
        },
        {
            "name": "ReturnSomething",
            "leader": "return ",
            "children": [
                {
                    "kind": "grammar",
                    "relation": "contents",
                    "nonterminal": "expr",
                    "format": "InLine",
                    "follower": ""
                }
            ]
        },
        {
            "name": "Return",
            "leader": "return",
            "children": []
        },
        {
            "name": "Delete",
            "leader": "del",
            "children": [
                {
                    "kind": "grammar",
                    "relation": "targets",
                    "nonterminal": "comma_exprs",
                    "format": "InLine",
                    "follower": ""
                }
            ]
        },
        {
            "name": "Assign",
            "leader": "",
            "children": [
                {
                    "kind": "grammar",
                    "relation": "targets",
                    "nonterminal": "target_exprs",
                    "format": "InLine",
                    "follower": " = "
                },
                {
                    "kind": "grammar",
                    "relation": "contents",
                    "nonterminal": "expr",
                    "format": "InLine",
                    "follower": ""
                }
            ]
        },
        {
            "name": "AugAssign",
            "leader": "",
            "children": [
                {
                    "kind": "grammar",
                    "relation": "target",
                    "nonterminal": "expr",
                    "format": "InLine",
                    "follower": " "
                },
                {
                    "kind": "grammar",
                    "relation": "op",
                    "nonterminal": "operator",
                    "format": "InLine",
                    "follower": "= "
                },
                {
                    "kind": "grammar",
                    "relation": "contents",
                    "nonterminal": "expr",
                    "format": "InLine",
                    "follower": ""
                }
            ]
        },
        {
            "name": "TypedAssign",
            "leader": "",
            "children": [
                {
                    "kind": "grammar",
                    "relation": "target",
                    "nonterminal": "expr",
                    "format": "InLine",
                    "follower": " : "
                },
                {
                    "kind": "grammar",
                    "relation": "type",
                    "nonterminal": "expr",
                    "format": "InLine",
                    "follower": " = "
                },
                {
                    "kind": "grammar",
                    "relation": "contents",
                    "nonterminal": "expr",
                    "format": "InLine",
                    "follower": ""
                }
            ]
        },
        {
            "name": "TypedDeclare",
            "leader": "",
            "children": [
                {
                    "kind": "grammar",
                    "relation": "target",
                    "nonterminal": "expr",
                    "format": "InLine",
                    "follower": " : "
                },
                {
                    "kind": "grammar",
                    "relation": "type",
                    "nonterminal": "expr",
                    "format": "InLine",
                    "follower": ""
                }
            ]
        },
        {
            "name": "For",
            "leader": "for ",
            "children": [
                {
                    "kind": "grammar",
                    "relation": "target",
                    "nonterminal": "expr",
                    "format": "InLine",
                    "follower": " in "
                },
                {
                    "kind": "grammar",
                    "relation": "iter",
                    "nonterminal": "expr",
                    "format": "InLine",
                    "follower": " : "
                },
                {
                    "kind": "grammar",
                    "relation": "body",
                    "nonterminal": "statements",
                    "format": "IndentLine",
                    "follower": ""
                }
            ]
        },
        {
            "name": "ForElse",
            "leader": "for ",
            "children": [
                {
                    "kind": "grammar",
                    "relation": "target",
                    "nonterminal": "expr",
                    "format": "InLine",
                    "follower": " in "
                },
                {
                    "kind": "grammar",
                    "relation": "iter",
                    "nonterminal": "expr",
                    "format": "InLine",
                    "follower": " : "
                },
                {
                    "kind": "grammar",
                    "relation": "body",
                    "nonterminal": "statements",
                    "format": "IndentLine",
                    "follower": ""
                },
                {
                    "kind": "grammar",
                    "relation": "orelse",
                    "nonterminal": "ElseBlock",
                    "format": "NewLine",
                    "follower": ""
                }
            ]
        },
        {
            "name": "AsyncFor",
            "leader": "async for ",
            "children": [
                {
                    "kind": "grammar",
                    "relation": "target",
                    "nonterminal": "expr",
                    "format": "InLine",
                    "follower": " in "
                },
                {
                    "kind": "grammar",
                    "relation": "iter",
                    "nonterminal": "expr",
                    "format": "InLine",
                    "follower": " : "
                },
                {
                    "kind": "grammar",
                    "relation": "body",
                    "nonterminal": "statements",
                    "format": "IndentLine",
                    "follower": ""
                }
            ]
        },
        {
            "name": "AsyncForElse",
            "leader": "async for ",
            "children": [
                {
                    "kind": "grammar",
                    "relation": "target",
                    "nonterminal": "expr",
                    "format": "InLine",
                    "follower": " in "
                },
                {
                    "kind": "grammar",
                    "relation": "iter",
                    "nonterminal": "expr",
                    "format": "InLine",
                    "follower": " : "
                },
                {
                    "kind": "grammar",
                    "relation": "body",
                    "nonterminal": "statements",
                    "format": "IndentLine",
                    "follower": ""
                },
                {
                    "kind": "grammar",
                    "relation": "orelse",
                    "nonterminal": "ElseBlock",
                    "format": "NewLine",
                    "follower": ""
                }
            ]
        },
        {
            "name": "While",
            "leader": "while ",
            "children": [
                {
                    "kind": "grammar",
                    "relation": "test",
                    "nonterminal": "expr",
                    "format": "InLine",
                    "follower": ": "
                },
                {
                    "kind": "grammar",
                    "relation": "body",
                    "nonterminal": "statements",
                    "format": "IndentLine",
                    "follower": ""
                }
            ]
        },
        {
            "name": "WhileElse",
            "leader": "while ",
            "children": [
                {
                    "kind": "grammar",
                    "relation": "test",
                    "nonterminal": "expr",
                    "format": "InLine",
                    "follower": ": "
                },
                {
                    "kind": "grammar",
                    "relation": "body",
                    "nonterminal": "statements",
                    "format": "IndentLine",
                    "follower": ""
                },
                {
                    "kind": "grammar",
                    "relation": "orelse",
                    "nonterminal": "ElseBlock",
                    "format": "NewLine",
                    "follower": ""
                }
            ]
        },
        {
            "name": "If",
            "leader": "if ",
            "children": [
                {
                    "kind": "grammar",
                    "relation": "test",
                    "nonterminal": "expr",
                    "format": "InLine",
                    "follower": ": "
                },
                {
                    "kind": "grammar",
                    "relation": "body",
                    "nonterminal": "statements",
                    "format": "IndentLine",
                    "follower": ""
                },
                {
                    "kind": "grammar",
                    "relation": "orelse",
                    "nonterminal": "conditions",
                    "format": "InLine",
                    "follower": ""
                }
            ]
        },
        {
            "name": "With",
            "leader": "with ",
            "children": [
                {
                    "kind": "grammar",
                    "relation": "items",
                    "nonterminal": "sequence_Withitem",
                    "format": "InLine",
                    "follower": ":"
                },
                {
                    "kind": "grammar",
                    "relation": "body",
                    "nonterminal": "statements",
                    "format": "IndentLine",
                    "follower": ""
                }
            ]
        },
        {
            "name": "AsyncWith",
            "leader": "async with ",
            "children": [
                {
                    "kind": "grammar",
                    "relation": "items",
                    "nonterminal": "sequence_Withitem",
                    "format": "InLine",
                    "follower": ":"
                },
                {
                    "kind": "grammar",
                    "relation": "body",
                    "nonterminal": "statements",
                    "format": "IndentLine",
                    "follower": ""
                }
            ]
        },
        {
            "name": "Raise",
            "leader": "raise",
            "children": []
        },
        {
            "name": "RaiseExc",
            "leader": "raise ",
            "children": [
                {
                    "kind": "grammar",
                    "relation": "exc",
                    "nonterminal": "expr",
                    "format": "IndentLine",
                    "follower": ""
                }
            ]
        },
        {
            "name": "RaiseFrom",
            "leader": "raise ",
            "children": [
                {
                    "kind": "grammar",
                    "relation": "exc",
                    "nonterminal": "expr",
                    "format": "InLine",
                    "follower": " from "
                },
                {
                    "kind": "grammar",
                    "relation": "caus",
                    "nonterminal": "expr",
                    "format": "InLine",
                    "follower": ""
                }
            ]
        },
        {
            "name": "Try",
            "leader": "try:",
            "children": [
                {
                    "kind": "grammar",
                    "relation": "body",
                    "nonterminal": "statements",
                    "format": "IndentLine",
                    "follower": ""
                },
                {
                    "kind": "grammar",
                    "relation": "handlers",
                    "nonterminal": "sequence_ExceptHandler",
                    "format": "NewLine",
                    "follower": ""
                }
            ]
        },
        {
            "name": "TryElse",
            "leader": "try:",
            "children": [
                {
                    "kind": "grammar",
                    "relation": "body",
                    "nonterminal": "statements",
                    "format": "IndentLine",
                    "follower": ""
                },
                {
                    "kind": "grammar",
                    "relation": "handlers",
                    "nonterminal": "sequence_ExceptHandler",
                    "format": "NewLine",
                    "follower": ""
                },
                {
                    "kind": "grammar",
                    "relation": "orelse",
                    "nonterminal": "ElseBlock",
                    "format": "NewLine",
                    "follower": ""
                }
            ]
        },
        {
            "name": "TryFin",
            "leader": "try:",
            "children": [
                {
                    "kind": "grammar",
                    "relation": "body",
                    "nonterminal": "statements",
                    "format": "IndentLine",
                    "follower": ""
                },
                {
                    "kind": "grammar",
                    "relation": "handlers",
                    "nonterminal": "sequence_ExceptHandler",
                    "format": "NewLine",
                    "follower": ""
                },
                {
                    "kind": "grammar",
                    "relation": "fin",
                    "nonterminal": "FinallyBlock",
                    "format": "NewLine",
                    "follower": ""
                }
            ]
        },
        {
            "name": "TryElseFin",
            "leader": "try:",
            "children": [
                {
                    "kind": "grammar",
                    "relation": "body",
                    "nonterminal": "statements",
                    "format": "IndentLine",
                    "follower": ""
                },
                {
                    "kind": "grammar",
                    "relation": "handlers",
                    "nonterminal": "sequence_ExceptHandler",
                    "format": "NewLine",
                    "follower": ""
                },
                {
                    "kind": "grammar",
                    "relation": "orelse",
                    "nonterminal": "ElseBlock",
                    "format": "NewLine",
                    "follower": ""
                },
                {
                    "kind": "grammar",
                    "relation": "fin",
                    "nonterminal": "FinallyBlock",
                    "format": "NewLine",
                    "follower": ""
                }
            ]
        },
        {
            "name": "Assert",
            "leader": "assert ",
            "children": [
                {
                    "kind": "grammar",
                    "relation": "test",
                    "nonterminal": "expr",
                    "format": "InLine",
                    "follower": ""
                }
            ]
        },
        {
            "name": "AssertMsg",
            "leader": "assert ",
            "children": [
                {
                    "kind": "grammar",
                    "relation": "test",
                    "nonterminal": "expr",
                    "format": "InLine",
                    "follower": ", "
                },
                {
                    "kind": "grammar",
                    "relation": "msg",
                    "nonterminal": "expr",
                    "format": "InLine",
                    "follower": ""
                }
            ]
        },
        {
            "name": "Import",
            "leader": "import ",
            "children": [
                {
                    "kind": "grammar",
                    "relation": "names",
                    "nonterminal": "sequence_ImportName",
                    "format": "InLine",
                    "follower": ""
                }
            ]
        },
        {
            "name": "ImportFrom",
            "leader": "from ",
            "children": [
                {
                    "kind": "grammar",
                    "relation": "module",
                    "nonterminal": "module_id",
                    "format": "InLine",
                    "follower": " import "
                },
                {
                    "kind": "grammar",
                    "relation": "names",
                    "nonterminal": "sequence_ImportName",
                    "format": "InLine",
                    "follower": ""
                }
            ]
        },
        {
            "name": "ImportWildCard",
            "leader": "from ",
            "children": [
                {
                    "kind": "grammar",
                    "relation": "module",
                    "nonterminal": "module_id",
                    "format": "InLine",
                    "follower": " import *"
                }
            ]
        },
        {
            "name": "Global",
            "leader": "global ",
            "children": [
                {
                    "kind": "grammar",
                    "relation": "names",
                    "nonterminal": "sequence_var",
                    "format": "InLine",
                    "follower": ""
                }
            ]
        },
        {
            "name": "Nonlocal",
            "leader": "nonlocal ",
            "children": [
                {
                    "kind": "grammar",
                    "relation": "names",
                    "nonterminal": "sequence_var",
                    "format": "InLine",
                    "follower": ""
                }
            ]
        },
        {
            "name": "Expr",
            "leader": "",
            "children": [
                {
                    "kind": "grammar",
                    "relation": "contents",
                    "nonterminal": "expr",
                    "format": "InLine",
                    "follower": ""
                }
            ]
        },
        {
            "name": "Pass",
            "leader": "pass",
            "children": []
        },
        {
            "name": "Break",
            "leader": "break",
            "children": []
        },
        {
            "name": "Continue",
            "leader": "continue",
            "children": []
        }
    ],
    "expr": [
        {
            "name": "BoolOp",
            "leader": "(",
            "children": [
                {
                    "kind": "grammar",
                    "relation": "left",
                    "nonterminal": "expr",
                    "format": "InLine",
                    "follower": " "
                },
                {
                    "kind": "grammar",
                    "relation": "op",
                    "nonterminal": "boolop",
                    "format": "InLine",
                    "follower": " "
                },
                {
                    "kind": "grammar",
                    "relation": "right",
                    "nonterminal": "expr",
                    "format": "InLine",
                    "follower": ")"
                }
            ]
        },
        {
            "name": "NamedExpr",
            "leader": "",
            "children": [
                {
                    "kind": "grammar",
                    "relation": "target",
                    "nonterminal": "expr",
                    "format": "InLine",
                    "follower": " := "
                },
                {
                    "kind": "grammar",
                    "relation": "contents",
                    "nonterminal": "expr",
                    "format": "InLine",
                    "follower": ""
                }
            ]
        },
        {
            "name": "BinOp",
            "leader": "(",
            "children": [
                {
                    "kind": "grammar",
                    "relation": "left",
                    "nonterminal": "expr",
                    "format": "InLine",
                    "follower": " "
                },
                {
                    "kind": "grammar",
                    "relation": "op",
                    "nonterminal": "operator",
                    "format": "InLine",
                    "follower": " "
                },
                {
                    "kind": "grammar",
                    "relation": "right",
                    "nonterminal": "expr",
                    "format": "InLine",
                    "follower": ")"
                }
            ]
        },
        {
            "name": "UnaryOp",
            "leader": "(",
            "children": [
                {
                    "kind": "grammar",
                    "relation": "op",
                    "nonterminal": "unaryop",
                    "format": "InLine",
                    "follower": " "
                },
                {
                    "kind": "grammar",
                    "relation": "right",
                    "nonterminal": "expr",
                    "format": "InLine",
                    "follower": ")"
                }
            ]
        },
        {
            "name": "Lambda",
            "leader": "lambda ",
            "children": [
                {
                    "kind": "grammar",
                    "relation": "params",
                    "nonterminal": "parameters",
                    "format": "InLine",
                    "follower": " :"
                },
                {
                    "kind": "grammar",
                    "relation": "body",
                    "nonterminal": "expr",
                    "format": "InLine",
                    "follower": ""
                }
            ]
        },
        {
            "name": "IfExp",
            "leader": "",
            "children": [
                {
                    "kind": "grammar",
                    "relation": "body",
                    "nonterminal": "expr",
                    "format": "InLine",
                    "follower": "if "
                },
                {
                    "kind": "grammar",
                    "relation": "test",
                    "nonterminal": "expr",
                    "format": "InLine",
                    "follower": " else"
                },
                {
                    "kind": "grammar",
                    "relation": "orelse",
                    "nonterminal": "expr",
                    "format": "NewLine",
                    "follower": ""
                }
            ]
        },
        {
            "name": "Dictionary",
            "leader": "{",
            "children": [
                {
                    "kind": "grammar",
                    "relation": "contents",
                    "nonterminal": "dictionary_contents",
                    "format": "IndentLine",
                    "follower": "}"
                }
            ]
        },
        {
            "name": "EmptyDictionary",
            "leader": "{}",
            "children": []
        },
        {
            "name": "Set",
            "leader": "{",
            "children": [
                {
                    "kind": "grammar",
                    "relation": "contents",
                    "nonterminal": "comma_exprs",
                    "format": "IndentLine",
                    "follower": "}"
                }
            ]
        },
        {
            "name": "ListComp",
            "leader": "[",
            "children": [
                {
                    "kind": "grammar",
                    "relation": "contents",
                    "nonterminal": "expr",
                    "format": "IndentLine",
                    "follower": ""
                },
                {
                    "kind": "grammar",
                    "relation": "constraints",
                    "nonterminal": "comprehension_constraints",
                    "format": "IndentLine",
                    "follower": "]"
                }
            ]
        },
        {
            "name": "SetComp",
            "leader": "{",
            "children": [
                {
                    "kind": "grammar",
                    "relation": "contents",
                    "nonterminal": "expr",
                    "format": "IndentLine",
                    "follower": ""
                },
                {
                    "kind": "grammar",
                    "relation": "constraints",
                    "nonterminal": "comprehension_constraints",
                    "format": "IndentLine",
                    "follower": "}"
                }
            ]
        },
        {
            "name": "DictionaryComp",
            "leader": "{",
            "children": [
                {
                    "kind": "grammar",
                    "relation": "key",
                    "nonterminal": "expr",
                    "format": "IndentLine",
                    "follower": " : "
                },
                {
                    "kind": "grammar",
                    "relation": "contents",
                    "nonterminal": "expr",
                    "format": "InLine",
                    "follower": ""
                },
                {
                    "kind": "grammar",
                    "relation": "constraints",
                    "nonterminal": "comprehension_constraints",
                    "format": "IndentLine",
                    "follower": "}"
                }
            ]
        },
        {
            "name": "GeneratorExp",
            "leader": "(",
            "children": [
                {
                    "kind": "grammar",
                    "relation": "contents",
                    "nonterminal": "expr",
                    "format": "IndentLine",
                    "follower": ""
                },
                {
                    "kind": "grammar",
                    "relation": "constraints",
                    "nonterminal": "comprehension_constraints",
                    "format": "IndentLine",
                    "follower": ")"
                }
            ]
        },
        {
            "name": "Await",
            "leader": "await ",
            "children": [
                {
                    "kind": "grammar",
                    "relation": "contents",
                    "nonterminal": "expr",
                    "format": "InLine",
                    "follower": ""
                }
            ]
        },
        {
            "name": "YieldNothing",
            "leader": "yield",
            "children": []
        },
        {
            "name": "Yield",
            "leader": "yield ",
            "children": [
                {
                    "kind": "grammar",
                    "relation": "contents",
                    "nonterminal": "expr",
                    "format": "InLine",
                    "follower": ""
                }
            ]
        },
        {
            "name": "YieldFrom",
            "leader": "yield from ",
            "children": [
                {
                    "kind": "grammar",
                    "relation": "contents",
                    "nonterminal": "expr",
                    "format": "InLine",
                    "follower": ""
                }
            ]
        },
        {
            "name": "Compare",
            "leader": "",
            "children": [
                {
                    "kind": "grammar",
                    "relation": "left",
                    "nonterminal": "expr",
                    "format": "InLine",
                    "follower": " "
                },
                {
                    "kind": "grammar",
                    "relation": "comps",
                    "nonterminal": "comparisons",
                    "format": "InLine",
                    "follower": ""
                }
            ]
        },
        {
            "name": "Call",
            "leader": "",
            "children": [
                {
                    "kind": "grammar",
                    "relation": "func",
                    "nonterminal": "expr",
                    "format": "InLine",
                    "follower": "()"
                }
            ]
        },
        {
            "name": "CallArgs",
            "leader": "",
            "children": [
                {
                    "kind": "grammar",
                    "relation": "func",
                    "nonterminal": "expr",
                    "format": "InLine",
                    "follower": "("
                },
                {
                    "kind": "grammar",
                    "relation": "args",
                    "nonterminal": "arguments",
                    "format": "InLine",
                    "follower": ")"
                }
            ]
        },
        {
            "name": "Integer",
            "leader": "",
            "children": [
                {
                    "kind": "vocab",
                    "relation": "contents",
                    "choices_id": "integer"
                }
            ]
        },
        {
            "name": "Float",
            "leader": "",
            "children": [
                {
                    "kind": "vocab",
                    "relation": "contents",
                    "choices_id": "float"
                }
            ]
        },
        {
            "name": "ConcatString",
            "leader": "",
            "children": [
                {
                    "kind": "grammar",
                    "relation": "contents",
                    "nonterminal": "sequence_string",
                    "format": "InLine",
                    "follower": ""
                }
            ]
        },
        {
            "name": "True_",
            "leader": "True",
            "children": []
        },
        {
            "name": "False_",
            "leader": "False",
            "children": []
        },
        {
            "name": "None_",
            "leader": "None",
            "children": []
        },
        {
            "name": "Ellip",
            "leader": "...",
            "children": []
        },
        {
            "name": "Attribute",
            "leader": "",
            "children": [
                {
                    "kind": "grammar",
                    "relation": "contents",
                    "nonterminal": "expr",
                    "format": "InLine",
                    "follower": "."
                },
                {
                    "kind": "vocab",
                    "relation": "name",
                    "choices_id": "identifier"
                }
            ]
        },
        {
            "name": "Subscript",
            "leader": "",
            "children": [
                {
                    "kind": "grammar",
                    "relation": "contents",
                    "nonterminal": "expr",
                    "format": "InLine",
                    "follower": "["
                },
                {
                    "kind": "grammar",
                    "relation": "slice",
                    "nonterminal": "expr",
                    "format": "InLine",
                    "follower": "]"
                }
            ]
        },
        {
            "name": "Starred",
            "leader": "*",
            "children": [
                {
                    "kind": "grammar",
                    "relation": "contents",
                    "nonterminal": "expr",
                    "format": "InLine",
                    "follower": ""
                }
            ]
        },
        {
            "name": "Name",
            "leader": "",
            "children": [
                {
                    "kind": "vocab",
                    "relation": "contents",
                    "choices_id": "identifier"
                }
            ]
        },
        {
            "name": "List",
            "leader": "[",
            "children": [
                {
                    "kind": "grammar",
                    "relation": "contents",
                    "nonterminal": "comma_exprs",
                    "format": "InLine",
                    "follower": "]"
                }
            ]
        },
        {
            "name": "EmptyList",
            "leader": "[]",
            "children": []
        },
        {
            "name": "Tuple",
            "leader": "(",
            "children": [
                {
                    "kind": "grammar",
                    "relation": "contents",
                    "nonterminal": "comma_exprs",
                    "format": "InLine",
                    "follower": ")"
                }
            ]
        },
        {
            "name": "EmptyTuple",
            "leader": "()",
            "children": []
        },
        {
            "name": "Slice",
            "leader": "",
            "children": [
                {
                    "kind": "grammar",
                    "relation": "lower",
                    "nonterminal": "option_expr",
                    "format": "InLine",
                    "follower": ":"
                },
                {
                    "kind": "grammar",
                    "relation": "upper",
                    "nonterminal": "option_expr",
                    "format": "InLine",
                    "follower": ":"
                },
                {
                    "kind": "grammar",
                    "relation": "step",
                    "nonterminal": "option_expr",
                    "format": "InLine",
                    "follower": ""
                }
            ]
        }
    ],
    "boolop": [
        {
            "name": "And",
            "leader": "and",
            "children": []
        },
        {
            "name": "Or",
            "leader": "or",
            "children": []
        }
    ],
    "operator": [
        {
            "name": "Add",
            "leader": "+",
            "children": []
        },
        {
            "name": "Sub",
            "leader": "-",
            "children": []
        },
        {
            "name": "Mult",
            "leader": "*",
            "children": []
        },
        {
            "name": "MatMult",
            "leader": "@",
            "children": []
        },
        {
            "name": "Div",
            "leader": "/",
            "children": []
        },
        {
            "name": "Mod",
            "leader": "%",
            "children": []
        },
        {
            "name": "Pow",
            "leader": "**",
            "children": []
        },
        {
            "name": "LShift",
            "leader": "<<",
            "children": []
        },
        {
            "name": "RShift",
            "leader": ">>",
            "children": []
        },
        {
            "name": "BitOr",
            "leader": "|",
            "children": []
        },
        {
            "name": "BitXor",
            "leader": "^",
            "children": []
        },
        {
            "name": "BitAnd",
            "leader": "&",
            "children": []
        },
        {
            "name": "FloorDiv",
            "leader": "//",
            "children": []
        }
    ],
    "unaryop": [
        {
            "name": "Invert",
            "leader": "~",
            "children": []
        },
        {
            "name": "Not",
            "leader": "not",
            "children": []
        },
        {
            "name": "UAdd",
            "leader": "+",
            "children": []
        },
        {
            "name": "USub",
            "leader": "-",
            "children": []
        }
    ],
    "cmpop": [
        {
            "name": "Eq",
            "leader": "==",
            "children": []
        },
        {
            "name": "NotEq",
            "leader": "!=",
            "children": []
        },
        {
            "name": "Lt",
            "leader": "<",
            "children": []
        },
        {
            "name": "LtE",
            "leader": "<=",
            "children": []
        },
        {
            "name": "Gt",
            "leader": ">",
            "children": []
        },
        {
            "name": "GtE",
            "leader": ">=",
            "children": []
        },
        {
            "name": "Is",
            "leader": "is",
            "children": []
        },
        {
            "name": "IsNot",
            "leader": "is not",
            "children": []
        },
        {
            "name": "In",
            "leader": "in",
            "children": []
        },
        {
            "name": "NotIn",
            "leader": "not in",
            "children": []
        }
    ],
    "constraint": [
        {
            "name": "AsyncConstraint",
            "leader": "async for ",
            "children": [
                {
                    "kind": "grammar",
                    "relation": "target",
                    "nonterminal": "expr",
                    "format": "InLine",
                    "follower": " in "
                },
                {
                    "kind": "grammar",
                    "relation": "search_space",
                    "nonterminal": "expr",
                    "format": "InLine",
                    "follower": ""
                },
                {
                    "kind": "grammar",
                    "relation": "filts",
                    "nonterminal": "constraint_filters",
                    "format": "InLine",
                    "follower": ""
                }
            ]
        },
        {
            "name": "Constraint",
            "leader": "for ",
            "children": [
                {
                    "kind": "grammar",
                    "relation": "target",
                    "nonterminal": "expr",
                    "format": "InLine",
                    "follower": " in "
                },
                {
                    "kind": "grammar",
                    "relation": "search_space",
                    "nonterminal": "expr",
                    "format": "InLine",
                    "follower": ""
                },
                {
                    "kind": "grammar",
                    "relation": "filts",
                    "nonterminal": "constraint_filters",
                    "format": "InLine",
                    "follower": ""
                }
            ]
        }
    ]
}